arrgh/__init__.py
arrgh/arrgh.py
arrgh-1.0.0.dist-info/LICENSE
arrgh-1.0.0.dist-info/METADATA
arrgh-1.0.0.dist-info/WHEEL
arrgh-1.0.0.dist-info/top_level.txt
arrgh-1.0.0.dist-info/RECORD
