Metadata-Version: 2.1
Name: arrgh
Version: 1.0.0
Summary: A small python utility to pretty-print a table summarizing arrays & scalars from numpy, pytorch, etc.
Author-email: Nicholas Sharp <nmwsharp@gmail.com>
Maintainer-email: Nicholas Sharp <nmwsharp@gmail.com>
License: MIT License
Project-URL: Homepage, https://github.com/nmwsharp/arrgh
Keywords: printing,debugging,logging,tensor,numpy,pytorch,jax
Requires-Python: >=3.7
License-File: LICENSE
